{"data":[{"openId":"resalb202004110434u4prpfj5","title":"难忘的英语语法系统课程（持续更新）","cover":"album/cover/3cf6e1d64c290d59bf3d2f661e040791.jpg","introduction":null,"partnerOpenId":"usrptn20200403083924x8rusp","countNum":793,"sectionId":"1001,1002,1003","subjectId":"1003","editionId":"1001","gradeId":"1006,1018,1019,1020,1003,1004,1005,gao_1,gao_2,gao_3","volumeId":"1001,1002","periodId":"1005","regimentationIds":"10006,10006","secondRegimentationIds":"10116,10231","hiddenAt":null,"stopSoldAt":null,"hiddenByOfficialAt":null,"stopSoldByOfficialAt":null,"price":9900,"discount":1.0,"vipDiscount":0.7979,"saleType":1,"vipOnly":false,"needAddress":false,"sequence":42,"tags":null,"partnerName":"山姆英语","partnerType":"企业","partnerLogo":"mp/partnerLogo/d720f0cd2546698fc49185f8340a86b3.jpg","publishedAt":"2021-06-23 14:40:51","updatedAt":"2021-06-23 14:40:51","recommendSequence":0,"resourceType":4,"vid":null,"albumContentNums":108,"syncInfoText":null,"periodName":null,"resourceOpenId":"resalb202004110434u4prpfj5","distribution":false,"totalClass":0,"displayType":4,"finish":false},{"openId":"resalb202004290535qcotg5a8","title":"雅思考试精讲","cover":"album/cover/29f3aff10be68ac37bfaeb10bbc8a9b7.png","introduction":"五步搞定雅思考试  轻松get答题模板 ","partnerOpenId":"usrptn202004241850mxduesb2","countNum":1,"sectionId":"1003,1004","subjectId":"1003","editionId":"1001","gradeId":"gao_1,gao_2,gao_3","volumeId":"1002,1001","periodId":"1005","regimentationIds":"10006","secondRegimentationIds":"10024,10116,10231,10121","hiddenAt":null,"stopSoldAt":null,"hiddenByOfficialAt":null,"stopSoldByOfficialAt":null,"price":19900,"discount":1.0,"vipDiscount":0.8,"saleType":1,"vipOnly":false,"needAddress":false,"sequence":0,"tags":null,"partnerName":"新学未","partnerType":"企业","partnerLogo":"mp/partnerLogo/57789295a0f623720c7e11ee350ed996.png","publishedAt":"2021-05-29 09:09:33","updatedAt":"2021-05-29 09:09:33","recommendSequence":null,"resourceType":4,"vid":null,"albumContentNums":51,"syncInfoText":null,"periodName":null,"resourceOpenId":"resalb202004290535qcotg5a8","distribution":false,"totalClass":51,"displayType":4,"finish":true},{"openId":"resalb20200703112115nmldj6","title":"特级名师点拨（高二英语语法）","cover":"album/cover/a63aef34141f5efaae9b68973975c184.jpg","introduction":null,"partnerOpenId":"usrptn2020060519181pvhpij5","countNum":9,"sectionId":"1003","subjectId":"1003","editionId":"1002","gradeId":"gao_2","volumeId":"1001,1002","periodId":"1005","regimentationIds":"10006,10006","secondRegimentationIds":"10116,10231","hiddenAt":null,"stopSoldAt":null,"hiddenByOfficialAt":null,"stopSoldByOfficialAt":null,"price":2890,"discount":1.0,"vipDiscount":0.0,"saleType":1,"vipOnly":false,"needAddress":false,"sequence":0,"tags":null,"partnerName":"掌上学教育","partnerType":"企业","partnerLogo":"mp/partnerLogo/a3917baef64cbb9aba3e314b8c71a42f.jpg","publishedAt":"2021-02-02 10:26:20","updatedAt":"2021-02-02 10:26:20","recommendSequence":null,"resourceType":4,"vid":null,"albumContentNums":16,"syncInfoText":null,"periodName":null,"resourceOpenId":"resalb20200703112115nmldj6","distribution":false,"totalClass":0,"displayType":4,"finish":false},{"openId":"resalb202106220506ck5em7vp","title":"8遍魔耳学句子","cover":"album/cover/d66679c08c97633ecd1c0c606be29d43.jpg","introduction":null,"partnerOpenId":"usrptn201912121054vep8erqj","countNum":5,"sectionId":"1001,1002,1003","subjectId":"1003","editionId":"1001","gradeId":"1001,1002,1003,1004,1005,1006,1018,1019,1020,gao_1,gao_2,gao_3","volumeId":"1001,1002","periodId":"1007","regimentationIds":"10006","secondRegimentationIds":"10116","hiddenAt":null,"stopSoldAt":null,"hiddenByOfficialAt":null,"stopSoldByOfficialAt":null,"price":9900,"discount":1.0,"vipDiscount":0.7979,"saleType":1,"vipOnly":false,"needAddress":false,"sequence":null,"tags":null,"partnerName":"十点课堂","partnerType":"企业","partnerLogo":"user/cover/b309ab033421aa0435e4e755ed532387.jpg","publishedAt":"2021-06-22 17:25:21","updatedAt":"2021-06-22 17:25:21","recommendSequence":null,"resourceType":4,"vid":null,"albumContentNums":82,"syncInfoText":null,"periodName":null,"resourceOpenId":"resalb202106220506ck5em7vp","distribution":null,"totalClass":81,"displayType":4,"finish":true}],"totalElements":4,"totalPages":1,"size":50,"number":0,"numberOfElements":4,"first":true,"last":true,"empty":false}