{"data":[{"openId":"resalb202004290535qcotg5a8","title":"雅思考试精讲","cover":"album/cover/29f3aff10be68ac37bfaeb10bbc8a9b7.png","introduction":"五步搞定雅思考试  轻松get答题模板 ","partnerOpenId":"usrptn202004241850mxduesb2","countNum":1,"sectionId":"1003,1004","subjectId":"1003","editionId":"1001","gradeId":"gao_1,gao_2,gao_3","volumeId":"1002,1001","periodId":"1005","regimentationIds":"10006","secondRegimentationIds":"10024,10116,10231,10121","hiddenAt":null,"stopSoldAt":null,"hiddenByOfficialAt":null,"stopSoldByOfficialAt":null,"price":19900,"discount":1.0,"vipDiscount":0.8,"saleType":1,"vipOnly":false,"needAddress":false,"sequence":0,"tags":null,"partnerName":"新学未","partnerType":"企业","partnerLogo":"mp/partnerLogo/57789295a0f623720c7e11ee350ed996.png","publishedAt":"2021-05-29 09:09:33","updatedAt":"2021-05-29 09:09:33","recommendSequence":null,"resourceType":4,"vid":null,"albumContentNums":51,"syncInfoText":null,"periodName":null,"resourceOpenId":"resalb202004290535qcotg5a8","distribution":false,"totalClass":51,"displayType":4,"finish":true},{"openId":"resalb201911190201trkmzw27","title":"高考九科指南——英语","cover":"album/cover/0fbbed8a7e4b8e624fa0eeb4e980db90.jpg","introduction":null,"partnerOpenId":"usrptn2019092712056e2cp8nb","countNum":2,"sectionId":"1003","subjectId":"1003","editionId":"1001","gradeId":"gao_3","volumeId":"1001,1002","periodId":"1004","regimentationIds":"10006,10006","secondRegimentationIds":"10231,10121","hiddenAt":null,"stopSoldAt":null,"hiddenByOfficialAt":null,"stopSoldByOfficialAt":null,"price":980,"discount":1.0,"vipDiscount":0.8,"saleType":1,"vipOnly":false,"needAddress":false,"sequence":0,"tags":null,"partnerName":"步步高","partnerType":"企业","partnerLogo":"mp/partnerLogo/dcbf4a5a518c404f46a3e39f4cdbeb39.jpg","publishedAt":"2021-02-02 10:29:39","updatedAt":"2021-02-02 10:29:39","recommendSequence":null,"resourceType":4,"vid":null,"albumContentNums":4,"syncInfoText":null,"periodName":null,"resourceOpenId":"resalb201911190201trkmzw27","distribution":false,"totalClass":0,"displayType":4,"finish":false},{"openId":"resalb202007080514uz5u6wkc","title":"高分技巧点拨（高三英语阅读理解）","cover":"album/cover/49ab3cac56302114ea7ade20c0169a83.jpg","introduction":null,"partnerOpenId":"usrptn2020060519181pvhpij5","countNum":3,"sectionId":"1003","subjectId":"1003","editionId":"1002","gradeId":"gao_3","volumeId":"1001,1002","periodId":"1005","regimentationIds":"10006,10006,10006","secondRegimentationIds":"10231,10121,10117","hiddenAt":null,"stopSoldAt":null,"hiddenByOfficialAt":null,"stopSoldByOfficialAt":null,"price":1990,"discount":1.0,"vipDiscount":0.0,"saleType":1,"vipOnly":false,"needAddress":false,"sequence":0,"tags":null,"partnerName":"掌上学教育","partnerType":"企业","partnerLogo":"mp/partnerLogo/a3917baef64cbb9aba3e314b8c71a42f.jpg","publishedAt":"2021-02-02 10:25:49","updatedAt":"2021-02-02 10:25:49","recommendSequence":null,"resourceType":4,"vid":null,"albumContentNums":9,"syncInfoText":null,"periodName":null,"resourceOpenId":"resalb202007080514uz5u6wkc","distribution":false,"totalClass":0,"displayType":4,"finish":false},{"openId":"resalb2020070805100nlb6vak","title":"特级名师精讲（高三英语语法专题）","cover":"album/cover/d5db951cf74aa8fb83a994e69c99ee95.jpg","introduction":null,"partnerOpenId":"usrptn2020060519181pvhpij5","countNum":1,"sectionId":"1003","subjectId":"1003","editionId":"1002","gradeId":"gao_3","volumeId":"1001,1002","periodId":"1005","regimentationIds":"10006,10006,10006","secondRegimentationIds":"10116,10231,10121","hiddenAt":null,"stopSoldAt":null,"hiddenByOfficialAt":null,"stopSoldByOfficialAt":null,"price":2690,"discount":1.0,"vipDiscount":0.0,"saleType":1,"vipOnly":false,"needAddress":false,"sequence":0,"tags":null,"partnerName":"掌上学教育","partnerType":"企业","partnerLogo":"mp/partnerLogo/a3917baef64cbb9aba3e314b8c71a42f.jpg","publishedAt":"2021-02-02 10:25:24","updatedAt":"2021-02-02 10:25:24","recommendSequence":null,"resourceType":4,"vid":null,"albumContentNums":13,"syncInfoText":null,"periodName":null,"resourceOpenId":"resalb2020070805100nlb6vak","distribution":false,"totalClass":0,"displayType":4,"finish":false},{"openId":"resalb202007080507ggqitvlh","title":"写作能力提升课（高三英语写作专题）","cover":"album/cover/40972aed5314af80cb9bc10fef24d2cc.jpg","introduction":null,"partnerOpenId":"usrptn2020060519181pvhpij5","countNum":2,"sectionId":"1003","subjectId":"1003","editionId":"1002","gradeId":"gao_3","volumeId":"1001,1002","periodId":"1005","regimentationIds":"10006,10006,10006","secondRegimentationIds":"10231,10121,10117","hiddenAt":null,"stopSoldAt":null,"hiddenByOfficialAt":null,"stopSoldByOfficialAt":null,"price":1990,"discount":1.0,"vipDiscount":0.0,"saleType":1,"vipOnly":false,"needAddress":false,"sequence":0,"tags":null,"partnerName":"掌上学教育","partnerType":"企业","partnerLogo":"mp/partnerLogo/a3917baef64cbb9aba3e314b8c71a42f.jpg","publishedAt":"2021-02-02 10:24:35","updatedAt":"2021-02-02 10:24:35","recommendSequence":null,"resourceType":4,"vid":null,"albumContentNums":6,"syncInfoText":null,"periodName":null,"resourceOpenId":"resalb202007080507ggqitvlh","distribution":false,"totalClass":0,"displayType":4,"finish":false},{"openId":"resalb202007080505l7pmqg0a","title":"解题方法指引（高三英语完形填空）","cover":"album/cover/55b711763a00cbbf363d597c82e57e31.jpg","introduction":null,"partnerOpenId":"usrptn2020060519181pvhpij5","countNum":1,"sectionId":"1003","subjectId":"1003","editionId":"1002","gradeId":"gao_3","volumeId":"1001,1002","periodId":"1005","regimentationIds":"10006,10006,10006","secondRegimentationIds":"10231,10121,10117","hiddenAt":null,"stopSoldAt":null,"hiddenByOfficialAt":null,"stopSoldByOfficialAt":null,"price":1990,"discount":1.0,"vipDiscount":0.0,"saleType":1,"vipOnly":false,"needAddress":false,"sequence":0,"tags":null,"partnerName":"掌上学教育","partnerType":"企业","partnerLogo":"mp/partnerLogo/a3917baef64cbb9aba3e314b8c71a42f.jpg","publishedAt":"2021-02-02 10:24:14","updatedAt":"2021-02-02 10:24:14","recommendSequence":null,"resourceType":4,"vid":null,"albumContentNums":6,"syncInfoText":null,"periodName":null,"resourceOpenId":"resalb202007080505l7pmqg0a","distribution":false,"totalClass":0,"displayType":4,"finish":false},{"openId":"resalb2020032302380ci0490x","title":"高考报考讲座（精剪回放）","cover":"album/cover/103ecce38fe102d38dd3b81ba0e93f72.jpg","introduction":null,"partnerOpenId":"usrptn202003231359qclcsi8z","countNum":0,"sectionId":"1003","subjectId":"1005","editionId":"1001","gradeId":"gao_3","volumeId":"1001,1002","periodId":"1005","regimentationIds":"10001,10004,10006,10126,10133","secondRegimentationIds":"10106,10109,10121,10132,10139","hiddenAt":null,"stopSoldAt":null,"hiddenByOfficialAt":null,"stopSoldByOfficialAt":null,"price":0,"discount":0.01,"vipDiscount":0.01,"saleType":1,"vipOnly":false,"needAddress":false,"sequence":0,"tags":null,"partnerName":"铭人教育","partnerType":"企业","partnerLogo":"mp/partnerLogo/b4921604325392a9911ed8f0eecd30ea.jpg","publishedAt":"2020-12-29 09:52:28","updatedAt":"2020-12-29 09:52:28","recommendSequence":null,"resourceType":4,"vid":null,"albumContentNums":3,"syncInfoText":null,"periodName":null,"resourceOpenId":"resalb2020032302380ci0490x","distribution":false,"totalClass":0,"displayType":11,"finish":false},{"openId":"resalb2020071010182uaeq36j","title":"新高考解读","cover":"album/cover/22349ec4900ad3cca6e733876ee294d9.jpg","introduction":null,"partnerOpenId":"usrptn2020060519181pvhpij5","countNum":2,"sectionId":"1003","subjectId":"1005","editionId":"1001","gradeId":"gao_3","volumeId":"1001,1002","periodId":"1005","regimentationIds":"10001,10004,10006,10126,10133,10140,10146,10151,10160","secondRegimentationIds":"10106,10109,10121,10132,10139,10145,10150,10155,10163","hiddenAt":null,"stopSoldAt":null,"hiddenByOfficialAt":null,"stopSoldByOfficialAt":null,"price":1990,"discount":1.0,"vipDiscount":0.0,"saleType":1,"vipOnly":false,"needAddress":false,"sequence":0,"tags":null,"partnerName":"掌上学教育","partnerType":"企业","partnerLogo":"mp/partnerLogo/a3917baef64cbb9aba3e314b8c71a42f.jpg","publishedAt":"2020-07-10 14:40:35","updatedAt":"2020-07-10 14:40:35","recommendSequence":null,"resourceType":4,"vid":null,"albumContentNums":31,"syncInfoText":null,"periodName":null,"resourceOpenId":"resalb2020071010182uaeq36j","distribution":false,"totalClass":0,"displayType":4,"finish":false},{"openId":"resalb202007090847saro1e6w","title":"名师教你如何选学校（高考志愿填报）","cover":"album/cover/1c25904fc4d5bdbf950c54b0ab171332.jpg","introduction":null,"partnerOpenId":"usrptn2020060519181pvhpij5","countNum":1,"sectionId":"1003","subjectId":"1005","editionId":"1001","gradeId":"gao_3","volumeId":"1001,1002","periodId":"1005","regimentationIds":"10001,10004,10006,10126,10133,10140,10146,10151,10160","secondRegimentationIds":"10106,10109,10121,10132,10139,10145,10150,10155,10163","hiddenAt":null,"stopSoldAt":null,"hiddenByOfficialAt":null,"stopSoldByOfficialAt":null,"price":1990,"discount":1.0,"vipDiscount":0.0,"saleType":1,"vipOnly":false,"needAddress":false,"sequence":0,"tags":null,"partnerName":"掌上学教育","partnerType":"企业","partnerLogo":"mp/partnerLogo/a3917baef64cbb9aba3e314b8c71a42f.jpg","publishedAt":"2020-07-09 09:25:00","updatedAt":"2020-07-09 09:25:00","recommendSequence":null,"resourceType":4,"vid":null,"albumContentNums":12,"syncInfoText":null,"periodName":null,"resourceOpenId":"resalb202007090847saro1e6w","distribution":false,"totalClass":0,"displayType":4,"finish":false},{"openId":"resalb2020112402484z77bmvy","title":"英语形近词超快速辨析","cover":"album/cover/2fe6060bc5185cce80192a00700ae7bd.png","introduction":"100组最易混淆的形近词辨析，帮你花式记单词，考试不再靠蒙！","partnerOpenId":"usrptn202011241015orjivvkx","countNum":6,"sectionId":"1003,1004","subjectId":"1003","editionId":"1001,1070,1002,1003,1032,1004,1052,1053,1065","gradeId":"gao_1,gao_2,gao_3,1020","volumeId":"1001,1002","periodId":"1005","regimentationIds":"10006","secondRegimentationIds":"10024,10025,10117,10119,10121","hiddenAt":null,"stopSoldAt":null,"hiddenByOfficialAt":null,"stopSoldByOfficialAt":null,"price":9900,"discount":1.0,"vipDiscount":0.797981,"saleType":1,"vipOnly":false,"needAddress":false,"sequence":null,"tags":"英语,单词,考试,形近词,词汇","partnerName":"卡片山谷英语","partnerType":"个人","partnerLogo":"mp/partnerLogo/7f0ef97003c558a10fa1052f1ee31d99.png","publishedAt":"2021-03-29 16:36:22","updatedAt":"2021-03-29 16:36:22","recommendSequence":null,"resourceType":4,"vid":null,"albumContentNums":100,"syncInfoText":null,"periodName":null,"resourceOpenId":"resalb2020112402484z77bmvy","distribution":false,"totalClass":100,"displayType":4,"finish":true}],"totalElements":10,"totalPages":1,"size":50,"number":0,"numberOfElements":10,"first":true,"last":true,"empty":false}