{"data":[{"openId":"resalb202008141044kao7v0a6","title":"口语交际","cover":"album/cover/b5de647f05c84196b0b33f0d95ce772d.jpg","introduction":null,"partnerOpenId":"usrptn201911181133pnqqntch","countNum":26,"sectionId":"1001","subjectId":"1001","editionId":"1001","gradeId":"1001,1002,1003","volumeId":"1001,1002","periodId":"1005","regimentationIds":"10009","secondRegimentationIds":"10186","hiddenAt":null,"stopSoldAt":null,"hiddenByOfficialAt":null,"stopSoldByOfficialAt":null,"price":3990,"discount":1.0,"vipDiscount":0.7994,"saleType":1,"vipOnly":false,"needAddress":false,"sequence":0,"tags":null,"partnerName":"看鉴","partnerType":"企业","partnerLogo":"mp/partnerLogo/fa95608ea1e5abf703ff4c02d55acf06.jpg","publishedAt":"2021-05-10 16:09:13","updatedAt":"2021-05-10 16:09:13","recommendSequence":null,"resourceType":4,"vid":null,"albumContentNums":21,"syncInfoText":null,"periodName":null,"resourceOpenId":"resalb202008141044kao7v0a6","distribution":false,"totalClass":0,"displayType":4,"finish":false},{"openId":"resalb202004160354wj1t3uxq","title":"兔兔课堂•少儿主持启蒙课","cover":"album/cover/5cf5c0b4976e36ad6511ad6d7993804d.jpg","introduction":null,"partnerOpenId":"usrptn202004031409nudrjfsd","countNum":19,"sectionId":"1001","subjectId":"1001","editionId":"1070,1001,1002","gradeId":"1001,1002","volumeId":"1001,1002","periodId":"1005","regimentationIds":"10009,10187,10167","secondRegimentationIds":"10186,10188,10183","hiddenAt":null,"stopSoldAt":null,"hiddenByOfficialAt":null,"stopSoldByOfficialAt":null,"price":3450,"discount":1.0,"vipDiscount":0.8666,"saleType":1,"vipOnly":false,"needAddress":false,"sequence":0,"tags":null,"partnerName":"大榕树微课堂","partnerType":"企业","partnerLogo":"mp/partnerLogo/b79a7abc5893bccafb33c849e04fb072.jpg","publishedAt":"2020-11-06 13:57:17","updatedAt":"2020-11-06 13:57:17","recommendSequence":null,"resourceType":4,"vid":null,"albumContentNums":10,"syncInfoText":null,"periodName":null,"resourceOpenId":"resalb202004160354wj1t3uxq","distribution":false,"totalClass":0,"displayType":4,"finish":false},{"openId":"resalb202004160411bdnfhz57","title":"兔兔纠音课","cover":"album/cover/d7be9be6302c88a92be028cb9c4f1d85.jpg","introduction":null,"partnerOpenId":"usrptn202004031409nudrjfsd","countNum":44,"sectionId":"1001","subjectId":"1001","editionId":"1070","gradeId":"1001,1002,1003","volumeId":"1001,1002","periodId":"1005","regimentationIds":"10009,10167","secondRegimentationIds":"10186,10183","hiddenAt":null,"stopSoldAt":null,"hiddenByOfficialAt":null,"stopSoldByOfficialAt":null,"price":2950,"discount":1.0,"vipDiscount":0.6745,"saleType":1,"vipOnly":false,"needAddress":false,"sequence":0,"tags":null,"partnerName":"大榕树微课堂","partnerType":"企业","partnerLogo":"mp/partnerLogo/b79a7abc5893bccafb33c849e04fb072.jpg","publishedAt":"2020-11-06 13:52:10","updatedAt":"2020-11-06 13:52:10","recommendSequence":null,"resourceType":4,"vid":null,"albumContentNums":11,"syncInfoText":null,"periodName":null,"resourceOpenId":"resalb202004160411bdnfhz57","distribution":false,"totalClass":0,"displayType":4,"finish":false},{"openId":"resalb2021041509538u5re6q9","title":"少儿语言艺术大师课","cover":"album/cover/1ea0b9b57041be1846c5346eca659c31.jpg","introduction":null,"partnerOpenId":"usrptn202103291416aa9igshm","countNum":1,"sectionId":"1001","subjectId":"1001,1005","editionId":"1001","gradeId":"1001,1002,1003,1004,1005,1006","volumeId":"1001,1002","periodId":"1007","regimentationIds":"10009","secondRegimentationIds":"10013,10186","hiddenAt":null,"stopSoldAt":null,"hiddenByOfficialAt":null,"stopSoldByOfficialAt":null,"price":24900,"discount":1.0,"vipDiscount":0.79919,"saleType":1,"vipOnly":false,"needAddress":false,"sequence":null,"tags":null,"partnerName":"魔豆时代","partnerType":"企业","partnerLogo":"user/cover/1616998499332tuodgiqc.jpg","publishedAt":"2021-04-15 10:06:44","updatedAt":"2021-04-15 10:06:44","recommendSequence":null,"resourceType":4,"vid":null,"albumContentNums":48,"syncInfoText":null,"periodName":null,"resourceOpenId":"resalb2021041509538u5re6q9","distribution":false,"totalClass":0,"displayType":4,"finish":true},{"openId":"resalb202011301021y42hythx","title":"脱颖而出，12堂让孩子更自信的语言表达课","cover":"album/cover/eb352f8603bc3dc49f604049553f9844.jpg","introduction":null,"partnerOpenId":"usrptn201912121054vep8erqj","countNum":11,"sectionId":"1001","subjectId":"1001","editionId":"1001","gradeId":"1001,1002,1003,1004,1005,1006","volumeId":"1001,1002","periodId":"1005","regimentationIds":"10009","secondRegimentationIds":"10186","hiddenAt":null,"stopSoldAt":null,"hiddenByOfficialAt":null,"stopSoldByOfficialAt":null,"price":9900,"discount":1.0,"vipDiscount":0.79798,"saleType":1,"vipOnly":false,"needAddress":false,"sequence":null,"tags":null,"partnerName":"十点课堂","partnerType":"企业","partnerLogo":"user/cover/b309ab033421aa0435e4e755ed532387.jpg","publishedAt":"2020-11-30 10:35:25","updatedAt":"2020-11-30 10:35:25","recommendSequence":null,"resourceType":4,"vid":null,"albumContentNums":23,"syncInfoText":null,"periodName":null,"resourceOpenId":"resalb202011301021y42hythx","distribution":null,"totalClass":0,"displayType":4,"finish":true}],"totalElements":5,"totalPages":1,"size":50,"number":0,"numberOfElements":5,"first":true,"last":true,"empty":false}