{"data":[{"openId":"resalb2020042702435gyp2y3x","title":"小学数学三年级下册（北师大版）期末总复习","cover":"album/cover/a9668e18b9e4d933f1eeab2a04272bb2.png","introduction":"明确课程目标，在实际的情景中帮助学生记忆，用知识解决实际问题；举一反三，让学生体会到知识的重要性，培养学生的学习兴趣。","partnerOpenId":"usrptn202004241850mxduesb2","countNum":128,"sectionId":"1001","subjectId":"1002","editionId":"1061","gradeId":"1003","volumeId":"1002","periodId":"1005","regimentationIds":"10004","secondRegimentationIds":"10019,10166,10029,10111,10219","hiddenAt":null,"stopSoldAt":null,"hiddenByOfficialAt":null,"stopSoldByOfficialAt":null,"price":9900,"discount":1.0,"vipDiscount":0.8,"saleType":1,"vipOnly":false,"needAddress":false,"sequence":0,"tags":null,"partnerName":"新学未","partnerType":"企业","partnerLogo":"mp/partnerLogo/57789295a0f623720c7e11ee350ed996.png","publishedAt":"2021-06-07 17:24:14","updatedAt":"2021-06-07 17:24:14","recommendSequence":null,"resourceType":4,"vid":null,"albumContentNums":49,"syncInfoText":null,"periodName":null,"resourceOpenId":"resalb2020042702435gyp2y3x","distribution":false,"totalClass":49,"displayType":4,"finish":true},{"openId":"resalb202005290724kjifxy3o","title":"小学数学三年级下册（人教版）期末总复习","cover":"album/cover/26d583fb2929b23286857b9807770231.png","introduction":"课程通过练习趣味数学题，提高学生的学习主动性，让孩子多动脑筋，发散思维，爱上数学！","partnerOpenId":"usrptn202004241850mxduesb2","countNum":149,"sectionId":"1001","subjectId":"1002","editionId":"1002","gradeId":"1003","volumeId":"1002","periodId":"1005","regimentationIds":"10004","secondRegimentationIds":"10019,10166,10029,10111,10218","hiddenAt":null,"stopSoldAt":null,"hiddenByOfficialAt":null,"stopSoldByOfficialAt":null,"price":9900,"discount":1.0,"vipDiscount":0.8,"saleType":1,"vipOnly":false,"needAddress":false,"sequence":0,"tags":null,"partnerName":"新学未","partnerType":"企业","partnerLogo":"mp/partnerLogo/57789295a0f623720c7e11ee350ed996.png","publishedAt":"2021-06-05 11:44:08","updatedAt":"2021-06-05 11:44:08","recommendSequence":null,"resourceType":4,"vid":null,"albumContentNums":52,"syncInfoText":null,"periodName":null,"resourceOpenId":"resalb202005290724kjifxy3o","distribution":false,"totalClass":52,"displayType":4,"finish":true},{"openId":"resalb201909270219hk0c5o6h","title":"小学数学教材习题轻松解（西师版）三年级下","cover":"album/cover/1769195e5024ca8c6ff37b220045ff3d.jpg","introduction":"","partnerOpenId":"usrptn201909091502k0tm3lhi","countNum":114,"sectionId":"1001","subjectId":"1002","editionId":"1014","gradeId":"1003","volumeId":"1002","periodId":"1007","regimentationIds":"10004","secondRegimentationIds":"10019,10029","hiddenAt":null,"stopSoldAt":null,"hiddenByOfficialAt":null,"stopSoldByOfficialAt":null,"price":0,"discount":1.0,"vipDiscount":1.0,"saleType":2,"vipOnly":false,"needAddress":false,"sequence":0,"tags":null,"partnerName":"淘知学堂小学号","partnerType":"企业","partnerLogo":"mp/partnerLogo/9b6f62bdcab1960bd29016c13e0ba476.jpg","publishedAt":"2021-04-10 09:14:46","updatedAt":"2021-04-10 09:14:46","recommendSequence":null,"resourceType":4,"vid":null,"albumContentNums":9,"syncInfoText":null,"periodName":null,"resourceOpenId":"resalb201909270219hk0c5o6h","distribution":false,"totalClass":0,"displayType":4,"finish":false},{"openId":"resalb201909270219nqusw8ps","title":"小学数学教材习题轻松解（青岛六三）三年级下","cover":"album/cover/b611a273fff4c8638f5054495fc35b03.jpg","introduction":"","partnerOpenId":"usrptn201909091502k0tm3lhi","countNum":6,"sectionId":"1001","subjectId":"1002","editionId":"1020","gradeId":"1003","volumeId":"1002","periodId":"1007","regimentationIds":"10004","secondRegimentationIds":"10019,10029","hiddenAt":null,"stopSoldAt":null,"hiddenByOfficialAt":null,"stopSoldByOfficialAt":null,"price":0,"discount":1.0,"vipDiscount":1.0,"saleType":2,"vipOnly":false,"needAddress":false,"sequence":0,"tags":null,"partnerName":"淘知学堂小学号","partnerType":"企业","partnerLogo":"mp/partnerLogo/9b6f62bdcab1960bd29016c13e0ba476.jpg","publishedAt":"2021-04-10 09:06:21","updatedAt":"2021-04-10 09:06:21","recommendSequence":null,"resourceType":4,"vid":null,"albumContentNums":6,"syncInfoText":null,"periodName":null,"resourceOpenId":"resalb201909270219nqusw8ps","distribution":false,"totalClass":0,"displayType":4,"finish":false},{"openId":"resalb201909270219nycez4vh","title":"小学数学教材习题轻松解（北京版）三年级下","cover":"album/cover/6aead9c5eaa285cd10069661191d9c08.jpg","introduction":"","partnerOpenId":"usrptn201909091502k0tm3lhi","countNum":12,"sectionId":"1001","subjectId":"1002","editionId":"1012","gradeId":"1003","volumeId":"1002","periodId":"1007","regimentationIds":"10004","secondRegimentationIds":"10019,10029","hiddenAt":null,"stopSoldAt":null,"hiddenByOfficialAt":null,"stopSoldByOfficialAt":null,"price":0,"discount":1.0,"vipDiscount":1.0,"saleType":2,"vipOnly":false,"needAddress":false,"sequence":0,"tags":null,"partnerName":"淘知学堂小学号","partnerType":"企业","partnerLogo":"mp/partnerLogo/9b6f62bdcab1960bd29016c13e0ba476.jpg","publishedAt":"2021-04-10 09:04:05","updatedAt":"2021-04-10 09:04:05","recommendSequence":null,"resourceType":4,"vid":null,"albumContentNums":8,"syncInfoText":null,"periodName":null,"resourceOpenId":"resalb201909270219nycez4vh","distribution":false,"totalClass":0,"displayType":4,"finish":false},{"openId":"resalb2019092702191rpqenln","title":"小学数学教材习题轻松解（河北教育版）三年级下","cover":"album/cover/eede64f91f589da21ad80aa56ec3ac2a.jpg","introduction":"","partnerOpenId":"usrptn201909091502k0tm3lhi","countNum":6,"sectionId":"1001","subjectId":"1002","editionId":"1010","gradeId":"1003","volumeId":"1002","periodId":"1007","regimentationIds":"10004","secondRegimentationIds":"10019,10029","hiddenAt":null,"stopSoldAt":null,"hiddenByOfficialAt":null,"stopSoldByOfficialAt":null,"price":0,"discount":1.0,"vipDiscount":1.0,"saleType":2,"vipOnly":false,"needAddress":false,"sequence":0,"tags":null,"partnerName":"淘知学堂小学号","partnerType":"企业","partnerLogo":"mp/partnerLogo/9b6f62bdcab1960bd29016c13e0ba476.jpg","publishedAt":"2021-04-09 13:47:33","updatedAt":"2021-04-09 13:47:33","recommendSequence":null,"resourceType":4,"vid":null,"albumContentNums":6,"syncInfoText":null,"periodName":null,"resourceOpenId":"resalb2019092702191rpqenln","distribution":false,"totalClass":0,"displayType":4,"finish":false},{"openId":"resalb201909270219pfrfzchd","title":"小学数学教材习题轻松解（青岛五四）三年级下","cover":"album/cover/5a99b9de446607f70080a1815742968c.jpg","introduction":"","partnerOpenId":"usrptn201909091502k0tm3lhi","countNum":19,"sectionId":"1001","subjectId":"1002","editionId":"1021","gradeId":"1003","volumeId":"1002","periodId":"1007","regimentationIds":"10004","secondRegimentationIds":"10019,10029","hiddenAt":null,"stopSoldAt":null,"hiddenByOfficialAt":null,"stopSoldByOfficialAt":null,"price":0,"discount":1.0,"vipDiscount":1.0,"saleType":2,"vipOnly":false,"needAddress":false,"sequence":0,"tags":null,"partnerName":"淘知学堂小学号","partnerType":"企业","partnerLogo":"mp/partnerLogo/9b6f62bdcab1960bd29016c13e0ba476.jpg","publishedAt":"2021-04-09 11:56:05","updatedAt":"2021-04-09 11:56:05","recommendSequence":null,"resourceType":4,"vid":null,"albumContentNums":8,"syncInfoText":null,"periodName":null,"resourceOpenId":"resalb201909270219pfrfzchd","distribution":false,"totalClass":0,"displayType":4,"finish":false},{"openId":"resalb201909270219hre7in02","title":"小学数学教材习题轻松解（人教版）三年级下","cover":"album/cover/8dbc4c1d1e494639cc3804631acd8173.jpg","introduction":"","partnerOpenId":"usrptn201909091502k0tm3lhi","countNum":25,"sectionId":"1001","subjectId":"1002","editionId":"1002","gradeId":"1003","volumeId":"1002","periodId":"1007","regimentationIds":"10004","secondRegimentationIds":"10019,10029","hiddenAt":null,"stopSoldAt":null,"hiddenByOfficialAt":null,"stopSoldByOfficialAt":null,"price":0,"discount":1.0,"vipDiscount":1.0,"saleType":2,"vipOnly":false,"needAddress":false,"sequence":0,"tags":null,"partnerName":"淘知学堂小学号","partnerType":"企业","partnerLogo":"mp/partnerLogo/9b6f62bdcab1960bd29016c13e0ba476.jpg","publishedAt":"2021-04-09 10:51:51","updatedAt":"2021-04-09 10:51:51","recommendSequence":null,"resourceType":4,"vid":null,"albumContentNums":8,"syncInfoText":null,"periodName":null,"resourceOpenId":"resalb201909270219hre7in02","distribution":false,"totalClass":0,"displayType":4,"finish":false},{"openId":"resalb201909270219wq62wvf7","title":"小学数学教材习题轻松解（苏教版）三年级下","cover":"album/cover/2ac28403e400c9098b9962b0f31a8b6c.jpg","introduction":"","partnerOpenId":"usrptn201909091502k0tm3lhi","countNum":30,"sectionId":"1001","subjectId":"1002","editionId":"1006","gradeId":"1003","volumeId":"1002","periodId":"1007","regimentationIds":"10004","secondRegimentationIds":"10019,10029","hiddenAt":null,"stopSoldAt":null,"hiddenByOfficialAt":null,"stopSoldByOfficialAt":null,"price":0,"discount":1.0,"vipDiscount":1.0,"saleType":2,"vipOnly":false,"needAddress":false,"sequence":0,"tags":null,"partnerName":"淘知学堂小学号","partnerType":"企业","partnerLogo":"mp/partnerLogo/9b6f62bdcab1960bd29016c13e0ba476.jpg","publishedAt":"2021-04-09 10:37:27","updatedAt":"2021-04-09 10:37:27","recommendSequence":null,"resourceType":4,"vid":null,"albumContentNums":8,"syncInfoText":null,"periodName":null,"resourceOpenId":"resalb201909270219wq62wvf7","distribution":false,"totalClass":0,"displayType":4,"finish":false},{"openId":"resalb201909270219gbun8egx","title":"小学数学教材习题轻松解（北京师大版）三年级下","cover":"album/cover/610d5ce6384eb38d268ee73fa308fa37.jpg","introduction":"","partnerOpenId":"usrptn201909091502k0tm3lhi","countNum":12,"sectionId":"1001","subjectId":"1002","editionId":"1007,1061","gradeId":"1003","volumeId":"1002","periodId":"1007","regimentationIds":"10004","secondRegimentationIds":"10019,10029","hiddenAt":null,"stopSoldAt":null,"hiddenByOfficialAt":null,"stopSoldByOfficialAt":null,"price":0,"discount":1.0,"vipDiscount":1.0,"saleType":2,"vipOnly":false,"needAddress":false,"sequence":0,"tags":null,"partnerName":"淘知学堂小学号","partnerType":"企业","partnerLogo":"mp/partnerLogo/9b6f62bdcab1960bd29016c13e0ba476.jpg","publishedAt":"2021-04-09 10:27:38","updatedAt":"2021-04-09 10:27:38","recommendSequence":null,"resourceType":4,"vid":null,"albumContentNums":8,"syncInfoText":null,"periodName":null,"resourceOpenId":"resalb201909270219gbun8egx","distribution":false,"totalClass":0,"displayType":4,"finish":false},{"openId":"resalb202010270615powzv5qh","title":"课本同步辅导-小学数学三年级下册（青岛版）","cover":"album/cover/0ca48c4fb6d312f6d11277ceb6791070.jpg","introduction":"课程贴合小学数学三年级下册（青岛版）教材，课程主要包括：两位数乘一位数、长方形、正方形、年月日、小数的初步认识等内容。","partnerOpenId":"usrptn202004241850mxduesb2","countNum":23,"sectionId":"1001","subjectId":"1002","editionId":"1020","gradeId":"1003","volumeId":"1002","periodId":"1005","regimentationIds":"10004","secondRegimentationIds":"10019,10166,10022,10029,10111","hiddenAt":null,"stopSoldAt":null,"hiddenByOfficialAt":null,"stopSoldByOfficialAt":null,"price":9900,"discount":1.0,"vipDiscount":0.8,"saleType":1,"vipOnly":false,"needAddress":false,"sequence":null,"tags":null,"partnerName":"新学未","partnerType":"企业","partnerLogo":"mp/partnerLogo/57789295a0f623720c7e11ee350ed996.png","publishedAt":"2021-06-19 19:00:05","updatedAt":"2021-06-19 19:00:05","recommendSequence":null,"resourceType":4,"vid":null,"albumContentNums":48,"syncInfoText":null,"periodName":null,"resourceOpenId":"resalb202010270615powzv5qh","distribution":false,"totalClass":0,"displayType":4,"finish":false},{"openId":"resalb202010270618kgonmplv","title":"小学数学三年级下册（苏教版）期末总复习 (持续更新中)","cover":"album/cover/4b00222e8c0d0f92a4dfee3587b020f3.png","introduction":"本课程主要通过学习数的运算，基础几何图形，数据收集整理，且多练习趣味数学题，可以提高学生对数学的兴趣。","partnerOpenId":"usrptn202004241850mxduesb2","countNum":21,"sectionId":"1001","subjectId":"1002","editionId":"1006","gradeId":"1003","volumeId":"1002","periodId":"1005","regimentationIds":"10004","secondRegimentationIds":"10019,10166,10022,10029,10111","hiddenAt":null,"stopSoldAt":null,"hiddenByOfficialAt":null,"stopSoldByOfficialAt":null,"price":9900,"discount":1.0,"vipDiscount":0.8,"saleType":1,"vipOnly":false,"needAddress":false,"sequence":null,"tags":null,"partnerName":"新学未","partnerType":"企业","partnerLogo":"mp/partnerLogo/57789295a0f623720c7e11ee350ed996.png","publishedAt":"2021-06-05 16:55:46","updatedAt":"2021-06-05 16:55:46","recommendSequence":null,"resourceType":4,"vid":null,"albumContentNums":44,"syncInfoText":null,"periodName":null,"resourceOpenId":"resalb202010270618kgonmplv","distribution":false,"totalClass":0,"displayType":4,"finish":false}],"totalElements":12,"totalPages":1,"size":50,"number":0,"numberOfElements":12,"first":true,"last":true,"empty":false}