{"data":[{"openId":"resalb202105120148q0l0biai","title":"英语人教●PEP版三年级下册试卷下载","cover":"album/cover/a7e211c9beb03f9abaabbae995f07d7e.jpg","introduction":null,"partnerOpenId":"usrptn201909091502k0tm3lhi","countNum":6,"sectionId":"1001","subjectId":"1003","editionId":"1003","gradeId":"1003","volumeId":"1002","periodId":"1007","regimentationIds":"10006,10204","secondRegimentationIds":"10203,10215","hiddenAt":null,"stopSoldAt":null,"hiddenByOfficialAt":null,"stopSoldByOfficialAt":null,"price":1300,"discount":1.0,"vipDiscount":0.5,"saleType":2,"vipOnly":false,"needAddress":false,"sequence":null,"tags":"真题圈","partnerName":"淘知学堂小学号","partnerType":"企业","partnerLogo":"mp/partnerLogo/9b6f62bdcab1960bd29016c13e0ba476.jpg","publishedAt":"2021-05-12 13:51:24","updatedAt":"2021-05-12 13:51:24","recommendSequence":null,"resourceType":4,"vid":null,"albumContentNums":4,"syncInfoText":null,"periodName":null,"resourceOpenId":"resalb202105120148q0l0biai","distribution":null,"totalClass":0,"displayType":4,"finish":false},{"openId":"resalb202105050442ruc1hno0","title":"数学北师大版三年级下册试卷下载","cover":"album/cover/d444cbb9d696a74dee47ed2929ce7d93.jpg","introduction":null,"partnerOpenId":"usrptn201909091502k0tm3lhi","countNum":3,"sectionId":"1001","subjectId":"1002","editionId":"1007","gradeId":"1003","volumeId":"1002","periodId":"1007","regimentationIds":"10004,10204","secondRegimentationIds":"10202,10215","hiddenAt":null,"stopSoldAt":null,"hiddenByOfficialAt":null,"stopSoldByOfficialAt":null,"price":3600,"discount":1.0,"vipDiscount":0.5,"saleType":2,"vipOnly":false,"needAddress":false,"sequence":null,"tags":"真题圈","partnerName":"淘知学堂小学号","partnerType":"企业","partnerLogo":"mp/partnerLogo/9b6f62bdcab1960bd29016c13e0ba476.jpg","publishedAt":"2021-05-06 14:13:04","updatedAt":"2021-05-06 14:13:04","recommendSequence":null,"resourceType":4,"vid":null,"albumContentNums":3,"syncInfoText":null,"periodName":null,"resourceOpenId":"resalb202105050442ruc1hno0","distribution":null,"totalClass":3,"displayType":4,"finish":true},{"openId":"resalb202104280506ywhdmlv2","title":"数学苏教版三年级下册试卷下载","cover":"album/cover/8533fb6639327cde4814a509475df379.jpg","introduction":null,"partnerOpenId":"usrptn201909091502k0tm3lhi","countNum":4,"sectionId":"1001","subjectId":"1002","editionId":"1006","gradeId":"1003","volumeId":"1002","periodId":"1007","regimentationIds":"10004,10204","secondRegimentationIds":"10202,10215","hiddenAt":null,"stopSoldAt":null,"hiddenByOfficialAt":null,"stopSoldByOfficialAt":null,"price":1100,"discount":1.0,"vipDiscount":0.5,"saleType":2,"vipOnly":false,"needAddress":false,"sequence":null,"tags":"真题圈","partnerName":"淘知学堂小学号","partnerType":"企业","partnerLogo":"mp/partnerLogo/9b6f62bdcab1960bd29016c13e0ba476.jpg","publishedAt":"2021-04-28 17:06:59","updatedAt":"2021-04-28 17:06:59","recommendSequence":null,"resourceType":4,"vid":null,"albumContentNums":2,"syncInfoText":null,"periodName":null,"resourceOpenId":"resalb202104280506ywhdmlv2","distribution":null,"totalClass":0,"displayType":4,"finish":false},{"openId":"resalb202104280459xdn3xh1l","title":"数学RJ三年级下册试卷下载","cover":"album/cover/67e95949c5a0c13153e3467b6eec4bfc.jpg","introduction":null,"partnerOpenId":"usrptn201909091502k0tm3lhi","countNum":23,"sectionId":"1001","subjectId":"1002","editionId":"1002","gradeId":"1003","volumeId":"1002","periodId":"1007","regimentationIds":"10004,10204","secondRegimentationIds":"10202,10215","hiddenAt":null,"stopSoldAt":null,"hiddenByOfficialAt":null,"stopSoldByOfficialAt":null,"price":1000,"discount":1.0,"vipDiscount":0.5,"saleType":2,"vipOnly":false,"needAddress":false,"sequence":null,"tags":"真题圈","partnerName":"淘知学堂小学号","partnerType":"企业","partnerLogo":"mp/partnerLogo/9b6f62bdcab1960bd29016c13e0ba476.jpg","publishedAt":"2021-04-28 16:59:51","updatedAt":"2021-04-28 16:59:51","recommendSequence":null,"resourceType":4,"vid":null,"albumContentNums":2,"syncInfoText":null,"periodName":null,"resourceOpenId":"resalb202104280459xdn3xh1l","distribution":null,"totalClass":0,"displayType":4,"finish":false}],"totalElements":4,"totalPages":1,"size":50,"number":0,"numberOfElements":4,"first":true,"last":true,"empty":false}