{"data":[{"openId":"resalb202101290252t2hgtfky","title":"广东教育上海科技版初中物理八年级（下）教师资源包","cover":"album/cover/09cddb8f4245fd63a41ac97dde3a792f.jpg","introduction":null,"partnerOpenId":"usrptn201909291502skgwb7yy","countNum":0,"sectionId":"1002","subjectId":"1006","editionId":"1044","gradeId":"1019","volumeId":"1002","periodId":"1007","regimentationIds":"10187","secondRegimentationIds":"10195","hiddenAt":null,"stopSoldAt":null,"hiddenByOfficialAt":null,"stopSoldByOfficialAt":null,"price":4800,"discount":1.0,"vipDiscount":0.5,"saleType":2,"vipOnly":false,"needAddress":false,"sequence":null,"tags":null,"partnerName":"淘知学堂中学号","partnerType":"企业","partnerLogo":"mp/partnerLogo/eef5d981d05b825aaee8635b9d33e93e.jpg","publishedAt":"2021-02-02 14:49:20","updatedAt":"2021-02-02 14:49:20","recommendSequence":null,"resourceType":4,"vid":null,"albumContentNums":2,"syncInfoText":null,"periodName":null,"resourceOpenId":"resalb202101290252t2hgtfky","distribution":null,"totalClass":0,"displayType":4,"finish":false},{"openId":"resalb202101290251ozegeu19","title":"上海科技版初中物理八年级（下）教师资源包","cover":"album/cover/f58f7480783ee1992308c457542dbaba.jpg","introduction":null,"partnerOpenId":"usrptn201909291502skgwb7yy","countNum":0,"sectionId":"1002","subjectId":"1006","editionId":"1038","gradeId":"1019","volumeId":"1002","periodId":"1007","regimentationIds":"10187","secondRegimentationIds":"10195","hiddenAt":null,"stopSoldAt":null,"hiddenByOfficialAt":null,"stopSoldByOfficialAt":null,"price":4800,"discount":1.0,"vipDiscount":0.5,"saleType":2,"vipOnly":false,"needAddress":false,"sequence":null,"tags":null,"partnerName":"淘知学堂中学号","partnerType":"企业","partnerLogo":"mp/partnerLogo/eef5d981d05b825aaee8635b9d33e93e.jpg","publishedAt":"2021-02-02 14:47:27","updatedAt":"2021-02-02 14:47:27","recommendSequence":null,"resourceType":4,"vid":null,"albumContentNums":2,"syncInfoText":null,"periodName":null,"resourceOpenId":"resalb202101290251ozegeu19","distribution":null,"totalClass":0,"displayType":4,"finish":false},{"openId":"resalb202005290419952rhzsk","title":"人教版初中物理八年级（下）教师资源包","cover":"album/cover/3505a500c922c39a84ceb388e7a7b206.jpg","introduction":null,"partnerOpenId":"usrptn201909291502skgwb7yy","countNum":7,"sectionId":"1002","subjectId":"1006","editionId":"1002","gradeId":"1019","volumeId":"1002","periodId":"1007","regimentationIds":"10187","secondRegimentationIds":"10195","hiddenAt":null,"stopSoldAt":null,"hiddenByOfficialAt":null,"stopSoldByOfficialAt":null,"price":6900,"discount":1.0,"vipDiscount":0.5,"saleType":2,"vipOnly":false,"needAddress":false,"sequence":0,"tags":"教师中心","partnerName":"淘知学堂中学号","partnerType":"企业","partnerLogo":"mp/partnerLogo/eef5d981d05b825aaee8635b9d33e93e.jpg","publishedAt":"2021-01-30 17:30:48","updatedAt":"2021-01-30 17:30:48","recommendSequence":null,"resourceType":4,"vid":null,"albumContentNums":2,"syncInfoText":null,"periodName":null,"resourceOpenId":"resalb202005290419952rhzsk","distribution":false,"totalClass":2,"displayType":4,"finish":true},{"openId":"resalb202005300911mift06n1","title":"外语教研版初中英语八年级（下）教师资源包","cover":"album/cover/7d17ccfde1404cc7598540c80b0c7912.jpg","introduction":null,"partnerOpenId":"usrptn201909291502skgwb7yy","countNum":3,"sectionId":"1002","subjectId":"1003","editionId":"1033","gradeId":"1019","volumeId":"1002","periodId":"1005","regimentationIds":"10187","secondRegimentationIds":"10190","hiddenAt":null,"stopSoldAt":null,"hiddenByOfficialAt":null,"stopSoldByOfficialAt":null,"price":9000,"discount":1.0,"vipDiscount":0.5,"saleType":1,"vipOnly":false,"needAddress":false,"sequence":0,"tags":"教师中心","partnerName":"淘知学堂中学号","partnerType":"企业","partnerLogo":"mp/partnerLogo/eef5d981d05b825aaee8635b9d33e93e.jpg","publishedAt":"2021-01-30 11:41:33","updatedAt":"2021-01-30 11:41:33","recommendSequence":null,"resourceType":4,"vid":null,"albumContentNums":2,"syncInfoText":null,"periodName":null,"resourceOpenId":"resalb202005300911mift06n1","distribution":false,"totalClass":0,"displayType":4,"finish":false},{"openId":"resalb202101301125jaitejft","title":"译林牛津版初中英语八年级（下）教师资源包","cover":"album/cover/69775c0bbaf9e8fa7841f5e05560f7b2.jpg","introduction":null,"partnerOpenId":"usrptn201909291502skgwb7yy","countNum":1,"sectionId":"1002","subjectId":"1003","editionId":"1025","gradeId":"1019","volumeId":"1002","periodId":"1005","regimentationIds":"10187","secondRegimentationIds":"10190","hiddenAt":null,"stopSoldAt":null,"hiddenByOfficialAt":null,"stopSoldByOfficialAt":null,"price":12000,"discount":1.0,"vipDiscount":0.5,"saleType":2,"vipOnly":false,"needAddress":false,"sequence":null,"tags":null,"partnerName":"淘知学堂中学号","partnerType":"企业","partnerLogo":"mp/partnerLogo/eef5d981d05b825aaee8635b9d33e93e.jpg","publishedAt":"2021-01-30 11:26:09","updatedAt":"2021-01-30 11:26:09","recommendSequence":null,"resourceType":4,"vid":null,"albumContentNums":2,"syncInfoText":null,"periodName":null,"resourceOpenId":"resalb202101301125jaitejft","distribution":null,"totalClass":0,"displayType":4,"finish":false},{"openId":"resalb20200529101688vickmh","title":"统编版初中语文八年级（下）教师资源包","cover":"album/cover/cf6ce43e49f6257934a2564d56192f63.jpg","introduction":null,"partnerOpenId":"usrptn201909291502skgwb7yy","countNum":5,"sectionId":"1002","subjectId":"1001","editionId":"1070","gradeId":"1019","volumeId":"1002","periodId":"1005","regimentationIds":"10187","secondRegimentationIds":"10188","hiddenAt":null,"stopSoldAt":null,"hiddenByOfficialAt":null,"stopSoldByOfficialAt":null,"price":14000,"discount":1.0,"vipDiscount":0.5,"saleType":2,"vipOnly":false,"needAddress":false,"sequence":0,"tags":"教师中心","partnerName":"淘知学堂中学号","partnerType":"企业","partnerLogo":"mp/partnerLogo/eef5d981d05b825aaee8635b9d33e93e.jpg","publishedAt":"2021-01-30 11:04:43","updatedAt":"2021-01-30 11:04:43","recommendSequence":null,"resourceType":4,"vid":null,"albumContentNums":2,"syncInfoText":null,"periodName":null,"resourceOpenId":"resalb20200529101688vickmh","distribution":false,"totalClass":0,"displayType":4,"finish":false},{"openId":"resalb202006160221ulem4p3c","title":"人教版初中英语八年级（下）教师资源包","cover":"album/cover/75405fcf8b76f21385b24423ca2a085e.jpg","introduction":null,"partnerOpenId":"usrptn201909291502skgwb7yy","countNum":6,"sectionId":"1002","subjectId":"1003","editionId":"1002","gradeId":"1019","volumeId":"1002","periodId":"1005","regimentationIds":"10187","secondRegimentationIds":"10190","hiddenAt":null,"stopSoldAt":null,"hiddenByOfficialAt":null,"stopSoldByOfficialAt":null,"price":15000,"discount":1.0,"vipDiscount":0.5,"saleType":2,"vipOnly":false,"needAddress":false,"sequence":0,"tags":"教师中心","partnerName":"淘知学堂中学号","partnerType":"企业","partnerLogo":"mp/partnerLogo/eef5d981d05b825aaee8635b9d33e93e.jpg","publishedAt":"2021-01-30 10:47:47","updatedAt":"2021-01-30 10:47:47","recommendSequence":null,"resourceType":4,"vid":null,"albumContentNums":2,"syncInfoText":null,"periodName":null,"resourceOpenId":"resalb202006160221ulem4p3c","distribution":false,"totalClass":0,"displayType":4,"finish":false},{"openId":"resalb202005291055zl8p0or9","title":"人教版初中英语八年级（上）教师资源包","cover":"album/cover/5128b89895cf6b77031083cbe109fc3a.jpg","introduction":null,"partnerOpenId":"usrptn201909291502skgwb7yy","countNum":4,"sectionId":"1002","subjectId":"1003","editionId":"1002","gradeId":"1019","volumeId":"1001","periodId":"1005","regimentationIds":"10187","secondRegimentationIds":"10190","hiddenAt":null,"stopSoldAt":null,"hiddenByOfficialAt":null,"stopSoldByOfficialAt":null,"price":15000,"discount":1.0,"vipDiscount":0.5,"saleType":2,"vipOnly":false,"needAddress":false,"sequence":0,"tags":"教师中心","partnerName":"淘知学堂中学号","partnerType":"企业","partnerLogo":"mp/partnerLogo/eef5d981d05b825aaee8635b9d33e93e.jpg","publishedAt":"2020-10-13 16:37:59","updatedAt":"2020-10-13 16:37:59","recommendSequence":null,"resourceType":4,"vid":null,"albumContentNums":2,"syncInfoText":null,"periodName":null,"resourceOpenId":"resalb202005291055zl8p0or9","distribution":false,"totalClass":0,"displayType":4,"finish":false},{"openId":"resalb2020071607304jcuypwc","title":"外语教研版初中英语八年级（上）教师资源包","cover":"album/cover/f0d78ce07e7911633ba0fad7f2935436.jpg","introduction":null,"partnerOpenId":"usrptn201909291502skgwb7yy","countNum":1,"sectionId":"1002","subjectId":"1003","editionId":"1033","gradeId":"1019","volumeId":"1001","periodId":"1005","regimentationIds":"10187","secondRegimentationIds":"10190","hiddenAt":null,"stopSoldAt":null,"hiddenByOfficialAt":null,"stopSoldByOfficialAt":null,"price":10800,"discount":1.0,"vipDiscount":0.5,"saleType":2,"vipOnly":false,"needAddress":false,"sequence":0,"tags":"教师中心","partnerName":"淘知学堂中学号","partnerType":"企业","partnerLogo":"mp/partnerLogo/eef5d981d05b825aaee8635b9d33e93e.jpg","publishedAt":"2020-10-13 16:25:26","updatedAt":"2020-10-13 16:25:26","recommendSequence":null,"resourceType":4,"vid":null,"albumContentNums":2,"syncInfoText":null,"periodName":null,"resourceOpenId":"resalb2020071607304jcuypwc","distribution":false,"totalClass":0,"displayType":4,"finish":false},{"openId":"resalb202007170856labmvn1u","title":"译林牛津版初中英语八年级（上）教师资源包","cover":"album/cover/c3bba38102a5aa44e771802a5917fee6.jpg","introduction":null,"partnerOpenId":"usrptn201909291502skgwb7yy","countNum":0,"sectionId":"1002","subjectId":"1003","editionId":"1073","gradeId":"1019","volumeId":"1001","periodId":"1005","regimentationIds":"10187","secondRegimentationIds":"10190","hiddenAt":null,"stopSoldAt":null,"hiddenByOfficialAt":null,"stopSoldByOfficialAt":null,"price":12000,"discount":1.0,"vipDiscount":0.5,"saleType":2,"vipOnly":false,"needAddress":false,"sequence":0,"tags":"教师中心","partnerName":"淘知学堂中学号","partnerType":"企业","partnerLogo":"mp/partnerLogo/eef5d981d05b825aaee8635b9d33e93e.jpg","publishedAt":"2020-10-13 16:05:10","updatedAt":"2020-10-13 16:05:10","recommendSequence":null,"resourceType":4,"vid":null,"albumContentNums":2,"syncInfoText":null,"periodName":null,"resourceOpenId":"resalb202007170856labmvn1u","distribution":false,"totalClass":0,"displayType":4,"finish":false},{"openId":"resalb202005290953pa4xk5bi","title":"统编版初中语文八年级（上）教师资源包","cover":"album/cover/597ffe9fca0a38bfa2c44888e34f8c14.jpg","introduction":null,"partnerOpenId":"usrptn201909291502skgwb7yy","countNum":7,"sectionId":"1002","subjectId":"1001","editionId":"1070","gradeId":"1019","volumeId":"1001","periodId":"1005","regimentationIds":"10187","secondRegimentationIds":"10188","hiddenAt":null,"stopSoldAt":null,"hiddenByOfficialAt":null,"stopSoldByOfficialAt":null,"price":15400,"discount":1.0,"vipDiscount":0.5,"saleType":2,"vipOnly":false,"needAddress":false,"sequence":0,"tags":"教师中心","partnerName":"淘知学堂中学号","partnerType":"企业","partnerLogo":"mp/partnerLogo/eef5d981d05b825aaee8635b9d33e93e.jpg","publishedAt":"2020-09-23 15:14:14","updatedAt":"2020-09-23 15:14:14","recommendSequence":null,"resourceType":4,"vid":null,"albumContentNums":4,"syncInfoText":null,"periodName":null,"resourceOpenId":"resalb202005290953pa4xk5bi","distribution":false,"totalClass":0,"displayType":4,"finish":false},{"openId":"resalb202007270847z26otqok","title":"华东师大版初中数学八年级（上）教师资源包","cover":"album/cover/42c02868e5363cdedb4275f92e1d8d03.jpg","introduction":null,"partnerOpenId":"usrptn201909291502skgwb7yy","countNum":0,"sectionId":"1002","subjectId":"1002","editionId":"1037","gradeId":"1019","volumeId":"1001","periodId":"1005","regimentationIds":"10187","secondRegimentationIds":"10189","hiddenAt":null,"stopSoldAt":null,"hiddenByOfficialAt":null,"stopSoldByOfficialAt":null,"price":12300,"discount":1.0,"vipDiscount":0.5,"saleType":2,"vipOnly":false,"needAddress":false,"sequence":0,"tags":"教师中心","partnerName":"淘知学堂中学号","partnerType":"企业","partnerLogo":"mp/partnerLogo/eef5d981d05b825aaee8635b9d33e93e.jpg","publishedAt":"2020-09-11 16:31:54","updatedAt":"2020-09-11 16:31:54","recommendSequence":null,"resourceType":4,"vid":null,"albumContentNums":2,"syncInfoText":null,"periodName":null,"resourceOpenId":"resalb202007270847z26otqok","distribution":false,"totalClass":0,"displayType":4,"finish":false},{"openId":"resalb202009090411qcc3xgj5","title":"人教版初中数学八年级（上）教师资源包","cover":"album/cover/4bd0ab3866e7b93b245c7c81a7fc3a0f.jpg","introduction":null,"partnerOpenId":"usrptn201909291502skgwb7yy","countNum":0,"sectionId":"1002","subjectId":"1002","editionId":"1002","gradeId":"1019","volumeId":"1001","periodId":"1005","regimentationIds":"10187","secondRegimentationIds":"10189","hiddenAt":null,"stopSoldAt":null,"hiddenByOfficialAt":null,"stopSoldByOfficialAt":null,"price":14300,"discount":1.0,"vipDiscount":0.5,"saleType":1,"vipOnly":false,"needAddress":false,"sequence":null,"tags":null,"partnerName":"淘知学堂中学号","partnerType":"企业","partnerLogo":"mp/partnerLogo/eef5d981d05b825aaee8635b9d33e93e.jpg","publishedAt":"2020-09-09 16:12:37","updatedAt":"2020-09-09 16:12:37","recommendSequence":null,"resourceType":4,"vid":null,"albumContentNums":2,"syncInfoText":null,"periodName":null,"resourceOpenId":"resalb202009090411qcc3xgj5","distribution":false,"totalClass":0,"displayType":4,"finish":false},{"openId":"resalb202007111129m94cq5mb","title":"上海科技版初中物理八年级（上）教师资源包","cover":"album/cover/a758da3d1334cbe87834a40c280f35e7.jpg","introduction":null,"partnerOpenId":"usrptn201909291502skgwb7yy","countNum":1,"sectionId":"1002","subjectId":"1006","editionId":"1038","gradeId":"1019","volumeId":"1001","periodId":"1005","regimentationIds":"10187","secondRegimentationIds":"10195","hiddenAt":null,"stopSoldAt":null,"hiddenByOfficialAt":null,"stopSoldByOfficialAt":null,"price":7400,"discount":1.0,"vipDiscount":0.5,"saleType":2,"vipOnly":false,"needAddress":false,"sequence":0,"tags":"教师中心","partnerName":"淘知学堂中学号","partnerType":"企业","partnerLogo":"mp/partnerLogo/eef5d981d05b825aaee8635b9d33e93e.jpg","publishedAt":"2020-09-02 11:33:10","updatedAt":"2020-09-02 11:33:10","recommendSequence":null,"resourceType":4,"vid":null,"albumContentNums":2,"syncInfoText":null,"periodName":null,"resourceOpenId":"resalb202007111129m94cq5mb","distribution":false,"totalClass":0,"displayType":4,"finish":false},{"openId":"resalb2020072405003rpqj4gp","title":"上海科技版初中数学八年级（上）教师资源包","cover":"album/cover/6e39519cd47796a1b4d9a9f84bdbf44d.jpg","introduction":null,"partnerOpenId":"usrptn201909291502skgwb7yy","countNum":0,"sectionId":"1002","subjectId":"1002","editionId":"1038","gradeId":"1019","volumeId":"1001","periodId":"1005","regimentationIds":"10187","secondRegimentationIds":"10189","hiddenAt":null,"stopSoldAt":null,"hiddenByOfficialAt":null,"stopSoldByOfficialAt":null,"price":12000,"discount":1.0,"vipDiscount":0.5,"saleType":2,"vipOnly":false,"needAddress":false,"sequence":0,"tags":"教师中心","partnerName":"淘知学堂中学号","partnerType":"企业","partnerLogo":"mp/partnerLogo/eef5d981d05b825aaee8635b9d33e93e.jpg","publishedAt":"2020-08-19 10:56:59","updatedAt":"2020-08-19 10:56:59","recommendSequence":null,"resourceType":4,"vid":null,"albumContentNums":2,"syncInfoText":null,"periodName":null,"resourceOpenId":"resalb2020072405003rpqj4gp","distribution":false,"totalClass":0,"displayType":4,"finish":false},{"openId":"resalb2020052904157zc4tntp","title":"人教版初中物理八年级（上）教师资源包","cover":"album/cover/c07421b76307f2b0e0a8f786e69281c5.jpg","introduction":null,"partnerOpenId":"usrptn201909291502skgwb7yy","countNum":5,"sectionId":"1002","subjectId":"1006","editionId":"1002","gradeId":"1019","volumeId":"1001","periodId":"1005","regimentationIds":"10187","secondRegimentationIds":"10195","hiddenAt":null,"stopSoldAt":null,"hiddenByOfficialAt":null,"stopSoldByOfficialAt":null,"price":6400,"discount":1.0,"vipDiscount":0.5,"saleType":1,"vipOnly":false,"needAddress":false,"sequence":0,"tags":"教师中心","partnerName":"淘知学堂中学号","partnerType":"企业","partnerLogo":"mp/partnerLogo/eef5d981d05b825aaee8635b9d33e93e.jpg","publishedAt":"2020-07-23 15:34:04","updatedAt":"2020-07-23 15:34:04","recommendSequence":null,"resourceType":4,"vid":null,"albumContentNums":2,"syncInfoText":null,"periodName":null,"resourceOpenId":"resalb2020052904157zc4tntp","distribution":false,"totalClass":0,"displayType":4,"finish":false},{"openId":"resalb2020071102488wvw0dza","title":"广东教育上海科技版初中物理八年级（上）教师资源包","cover":"album/cover/6bf416c4189fc1ec45375a2c7002cfed.jpg","introduction":null,"partnerOpenId":"usrptn201909291502skgwb7yy","countNum":2,"sectionId":"1002","subjectId":"1006","editionId":"1044","gradeId":"1019","volumeId":"1001","periodId":"1005","regimentationIds":"10187","secondRegimentationIds":"10195","hiddenAt":null,"stopSoldAt":null,"hiddenByOfficialAt":null,"stopSoldByOfficialAt":null,"price":7400,"discount":1.0,"vipDiscount":0.5,"saleType":2,"vipOnly":false,"needAddress":false,"sequence":0,"tags":"教师中心","partnerName":"淘知学堂中学号","partnerType":"企业","partnerLogo":"mp/partnerLogo/eef5d981d05b825aaee8635b9d33e93e.jpg","publishedAt":"2020-07-15 08:12:50","updatedAt":"2020-07-15 08:12:50","recommendSequence":null,"resourceType":4,"vid":null,"albumContentNums":2,"syncInfoText":null,"periodName":null,"resourceOpenId":"resalb2020071102488wvw0dza","distribution":false,"totalClass":0,"displayType":4,"finish":false},{"openId":"resalb202005290237efpr2xp5","title":"统编版初中道德与法治八年级（下）教师资源包","cover":"album/cover/535232383287d8e24db249b9e0b2ca32.jpg","introduction":null,"partnerOpenId":"usrptn201909291502skgwb7yy","countNum":1,"sectionId":"1002","subjectId":"1012","editionId":"1070","gradeId":"1019","volumeId":"1002","periodId":"1005","regimentationIds":"10187","secondRegimentationIds":"10200","hiddenAt":null,"stopSoldAt":null,"hiddenByOfficialAt":null,"stopSoldByOfficialAt":null,"price":4000,"discount":1.0,"vipDiscount":0.5,"saleType":2,"vipOnly":false,"needAddress":false,"sequence":0,"tags":"教师中心","partnerName":"淘知学堂中学号","partnerType":"企业","partnerLogo":"mp/partnerLogo/eef5d981d05b825aaee8635b9d33e93e.jpg","publishedAt":"2020-07-10 11:37:22","updatedAt":"2020-07-10 11:37:22","recommendSequence":null,"resourceType":4,"vid":null,"albumContentNums":1,"syncInfoText":null,"periodName":null,"resourceOpenId":"resalb202005290237efpr2xp5","distribution":false,"totalClass":0,"displayType":4,"finish":false},{"openId":"resalb20200529030454wdzp69","title":"北师大版初中数学八年级（下）教师资源包","cover":"album/cover/52a904518e5510dd88e1665cc520d5bd.jpg","introduction":null,"partnerOpenId":"usrptn201909291502skgwb7yy","countNum":1,"sectionId":"1002","subjectId":"1002","editionId":"1061","gradeId":"1019","volumeId":"1002","periodId":"1005","regimentationIds":"10187","secondRegimentationIds":"10189","hiddenAt":null,"stopSoldAt":null,"hiddenByOfficialAt":null,"stopSoldByOfficialAt":null,"price":9600,"discount":1.0,"vipDiscount":0.5,"saleType":2,"vipOnly":false,"needAddress":false,"sequence":0,"tags":"教师中心","partnerName":"淘知学堂中学号","partnerType":"企业","partnerLogo":"mp/partnerLogo/eef5d981d05b825aaee8635b9d33e93e.jpg","publishedAt":"2020-06-13 16:55:01","updatedAt":"2020-06-13 16:55:01","recommendSequence":null,"resourceType":4,"vid":null,"albumContentNums":1,"syncInfoText":null,"periodName":null,"resourceOpenId":"resalb20200529030454wdzp69","distribution":false,"totalClass":0,"displayType":4,"finish":false},{"openId":"resalb202005291059md7jqx73","title":"人教版初中数学八年级（下）教师资源包","cover":"album/cover/128242188c080beded2af5444b2e7026.jpg","introduction":null,"partnerOpenId":"usrptn201909291502skgwb7yy","countNum":3,"sectionId":"1002","subjectId":"1002","editionId":"1002","gradeId":"1019","volumeId":"1002","periodId":"1005","regimentationIds":"10187","secondRegimentationIds":"10189","hiddenAt":null,"stopSoldAt":null,"hiddenByOfficialAt":null,"stopSoldByOfficialAt":null,"price":7800,"discount":1.0,"vipDiscount":0.5,"saleType":2,"vipOnly":false,"needAddress":false,"sequence":0,"tags":"教师中心","partnerName":"淘知学堂中学号","partnerType":"企业","partnerLogo":"mp/partnerLogo/eef5d981d05b825aaee8635b9d33e93e.jpg","publishedAt":"2020-06-13 16:54:35","updatedAt":"2020-06-13 16:54:35","recommendSequence":null,"resourceType":4,"vid":null,"albumContentNums":1,"syncInfoText":null,"periodName":null,"resourceOpenId":"resalb202005291059md7jqx73","distribution":false,"totalClass":0,"displayType":4,"finish":false},{"openId":"resalb202005290224uhv4qosa","title":"统编版初中历史八年级（下）教师资源包","cover":"album/cover/8d07b6e5f1009a972288233960638cdf.jpg","introduction":null,"partnerOpenId":"usrptn201909291502skgwb7yy","countNum":5,"sectionId":"1002","subjectId":"1010","editionId":"1070","gradeId":"1019","volumeId":"1002","periodId":"1005","regimentationIds":"10187","secondRegimentationIds":"10199","hiddenAt":null,"stopSoldAt":null,"hiddenByOfficialAt":null,"stopSoldByOfficialAt":null,"price":3800,"discount":1.0,"vipDiscount":0.5,"saleType":2,"vipOnly":false,"needAddress":false,"sequence":0,"tags":"教师中心","partnerName":"淘知学堂中学号","partnerType":"企业","partnerLogo":"mp/partnerLogo/eef5d981d05b825aaee8635b9d33e93e.jpg","publishedAt":"2020-06-13 16:54:26","updatedAt":"2020-06-13 16:54:26","recommendSequence":null,"resourceType":4,"vid":null,"albumContentNums":1,"syncInfoText":null,"periodName":null,"resourceOpenId":"resalb202005290224uhv4qosa","distribution":false,"totalClass":0,"displayType":4,"finish":false},{"openId":"resalb202005290950tw24cpt4","title":"人教版初中数学八年级（上）教师资源包","cover":"album/cover/6540f2f5aa053d9cfc4e99de5351369d.jpg","introduction":null,"partnerOpenId":"usrptn201909291502skgwb7yy","countNum":4,"sectionId":"1002","subjectId":"1002","editionId":"1002","gradeId":"1019","volumeId":"1001","periodId":"1005","regimentationIds":"10187","secondRegimentationIds":"10189","hiddenAt":null,"stopSoldAt":null,"hiddenByOfficialAt":null,"stopSoldByOfficialAt":null,"price":9200,"discount":1.0,"vipDiscount":0.5,"saleType":2,"vipOnly":false,"needAddress":false,"sequence":0,"tags":"教师中心","partnerName":"淘知学堂中学号","partnerType":"企业","partnerLogo":"mp/partnerLogo/eef5d981d05b825aaee8635b9d33e93e.jpg","publishedAt":"2020-06-13 16:53:45","updatedAt":"2020-06-13 16:53:45","recommendSequence":null,"resourceType":4,"vid":null,"albumContentNums":1,"syncInfoText":null,"periodName":null,"resourceOpenId":"resalb202005290950tw24cpt4","distribution":false,"totalClass":0,"displayType":4,"finish":false}],"totalElements":22,"totalPages":1,"size":50,"number":0,"numberOfElements":22,"first":true,"last":true,"empty":false}